blitzcurve/__init__.py
blitzcurve/compare.py
blitzcurve/fit.py
blitzcurve/test.py
blitzcurve/utils.py
blitzcurve-0.0.2.dist-info/METADATA
blitzcurve-0.0.2.dist-info/RECORD
blitzcurve-0.0.2.dist-info/WHEEL
blitzcurve-0.0.2.dist-info/top_level.txt
