Metadata-Version: 2.1
Name: blitzcurve
Version: 0.0.2
Summary: Time-resolved fluorescence anisotropy analysis.
Home-page: https://github.com/teese/blitzcurve
Author: Mark Teese and Philipp Heckmeier
Author-email: mark.teese@checkmytumhomepage.de
License: MIT
Download-URL: https://github.com/teese/blitzcurve/archive/0.0.2.tar.gz
Project-URL: LangoschLab, http://cbp.wzw.tum.de/index.php?id=9
Project-URL: TU_Munich, https://www.tum.de
Keywords: fluorescence FRET rotation curve savitzky golay anisotropy time resolved TRAM single molecule protein bioinformatics biophysics microscopy
Platform: UNKNOWN
Classifier: Programming Language :: Python :: 3.6
Classifier: License :: OSI Approved :: MIT License
Classifier: Intended Audience :: Science/Research
Classifier: Topic :: Scientific/Engineering :: Chemistry
Classifier: Topic :: Scientific/Engineering :: Physics
Requires-Dist: pandas
Requires-Dist: numpy
Requires-Dist: scipy
Requires-Dist: matplotlib
